mapget/LICENSE.txt
mapget/__init__.py
mapget/__main__.py
mapget/libmapget-http-datasource.a
mapget/libmapget-model.a
mapget/pymapget.cpython-312-darwin.so
mapget-2025.3.1.dist-info/METADATA
mapget-2025.3.1.dist-info/WHEEL
mapget-2025.3.1.dist-info/top_level.txt
mapget-2025.3.1.dist-info/RECORD
