Metadata-Version: 2.4
Name: mapget
Version: 2025.3.1
Summary: Python bindings for the mapget library.
Home-page: https://github.com/klebert-engineering/mapget
Author: Klebert Engineering
Author-email: 
Keywords: mapget
Requires-Python: >=3.9
Dynamic: author
Dynamic: home-page
Dynamic: keywords
Dynamic: requires-python
Dynamic: summary
